{"cameraMode":{"drawMode":0,"name":"Shaded","section":"Shading Mode"},"sceneLighting":true,"audioPlay":false,"sceneViewState":{"m_AlwaysRefresh":false,"showFog":true,"showSkybox":true,"showFlares":true,"showImageEffects":true,"showParticleSystems":true,"showVisualEffectGraphs":true,"m_FxEnabled":true},"in2DMode":false,"pivot":{"x":26.8778076171875,"y":0.7604179382324219,"z":1.1650505065917969},"rotation":{"x":-0.08921211957931519,"y":-0.8830498456954956,"z":0.1871168166399002,"w":-0.4210139214992523},"size":10.0,"orthographic":false}